LICENSE
gecs/catgec.py
gecs/catger.py
gecs/gec_base.py
gecs/lightgec.py
gecs/lightger.py
gecs/utils/gaussian_process_visualisation.py
gecs-0.36.1.dist-info/LICENSE
gecs-0.36.1.dist-info/METADATA
gecs-0.36.1.dist-info/WHEEL
gecs-0.36.1.dist-info/RECORD
